mindforge_ml/__init__.py
mindforge_ml/utils.py
mindforge_ml/visualization.py
mindforge_ml/supervised/__init__.py
mindforge_ml/supervised/model.py
mindforge_ml/supervised/classifier/__init__.py
mindforge_ml/supervised/classifier/model.py
mindforge_ml/unsupervised/__init__.py
mindforge_ml/unsupervised/model.py
mindforge_ml-0.2.0.dist-info/licenses/LICENSE
mindforge_ml-0.2.0.dist-info/METADATA
mindforge_ml-0.2.0.dist-info/WHEEL
mindforge_ml-0.2.0.dist-info/top_level.txt
mindforge_ml-0.2.0.dist-info/RECORD
