Metadata-Version: 2.4
Name: mindforge-ml
Version: 0.2.0
Summary: An open-source machine learning library for research and production, offering unified tools across deep learning, NLP, computer vision, reinforcement learning, and predictive analytics.
Home-page: https://github.com/Perfect-Aimers-Enterprise/mindforge
Author: Godsave Kawurem
Author-email: Godsave Kawurem <godsaveogbidor@gmail.com>
License: MIT
Project-URL: Homepage, https://github.com/Perfect-Aimers-Enterprise/mindforge
Project-URL: Bug Tracker, https://github.com/Perfect-Aimers-Enterprise/mindforge/issues
Keywords: machine learning,AI,scikit-learn,deep learning,pytorch,mindforge
Classifier: Development Status :: 3 - Alpha
Classifier: Intended Audience :: Science/Research
Classifier: Programming Language :: Python :: 3
Classifier: License :: OSI Approved :: MIT License
Classifier: Operating System :: OS Independent
Classifier: Topic :: Scientific/Engineering :: Artificial Intelligence
Requires-Python: >=3.8
License-File: LICENSE
Requires-Dist: numpy
Requires-Dist: pandas
Requires-Dist: transformers
Requires-Dist: scikit-learn
Requires-Dist: matplotlib
Requires-Dist: seaborn
Requires-Dist: torch
Requires-Dist: spacy
Dynamic: license-file
